
{"items":[{"name":"Úvod EIC","topicHref":"index.html","homepage":"index.html"},{"name":"Projekt","href":"api/EasyITCenter.BackendServer.yml","topicHref":"api/EasyITCenter.BackendServer.yml"},{"name":"Info Dokumentace","href":"EASY-DATA/SUMMARY.md","topicHref":"EASY-DATA/SUMMARY.md"},{"name":"Dev Šablony","href":"EASY-DATA/EICTemplates.md","topicHref":"EASY-DATA/EICTemplates.md"},{"name":"Struktura C#","href":"EASY-DATA/EasyITCenter-Server.md","topicHref":"EASY-DATA/EasyITCenter-Server.md"},{"name":"Online Ukázky","href":"EASY-DATA/EICExamplesOnline.md","topicHref":"EASY-DATA/EICExamplesOnline.md"}],"pdf":true}
